plantuml2cpp/__init__.py
plantuml2cpp/__main__.py
plantuml2cpp/codegen.py
plantuml2cpp/parser.py
plantuml2cpp-0.0.2.dist-info/LICENSE
plantuml2cpp-0.0.2.dist-info/METADATA
plantuml2cpp-0.0.2.dist-info/WHEEL
plantuml2cpp-0.0.2.dist-info/entry_points.txt
plantuml2cpp-0.0.2.dist-info/top_level.txt
plantuml2cpp-0.0.2.dist-info/RECORD
